segment_anything_onnx/__init__.py
segment_anything_onnx/cli.py
segment_anything_onnx/inference.py
segment_anything_onnx/sam_onnx.py
segment_anything_onnx-0.0.5.dist-info/LICENSE
segment_anything_onnx-0.0.5.dist-info/METADATA
segment_anything_onnx-0.0.5.dist-info/WHEEL
segment_anything_onnx-0.0.5.dist-info/top_level.txt
segment_anything_onnx-0.0.5.dist-info/RECORD
