Metadata-Version: 2.1
Name: segment_anything_onnx
Version: 0.0.5
Summary: Run Segment Anything with ONNX models
Author-email: Mike Prince <mike@mikeprince.com>
Project-URL: Homepage, https://github.com/whatstyle-ai/segment-anything-onnx
Project-URL: Issues, https://github.com/whatstyle-ai/segment-anything-onnx/issues
Classifier: Programming Language :: Python :: 3
Classifier: License :: OSI Approved :: MIT License
Classifier: Operating System :: OS Independent
Requires-Python: >=3.8
License-File: LICENSE
Requires-Dist: opencv-python
Requires-Dist: numpy
Requires-Dist: onnxruntime
